atmodata/__init__.py
atmodata/builder.py
atmodata/patching.py
atmodata/serialization.py
atmodata/utils.py
atmodata/version.py
atmodata/xarray_utils.py
atmodata/datasets/__init__.py
atmodata/datasets/weatherbench.py
atmodata/iter/__init__.py
atmodata/iter/tensor.py
atmodata/iter/util.py
atmodata/iter/xarray.py
atmodata/map/__init__.py
atmodata/tasks/__init__.py
atmodata/tasks/forecasting.py
atmodata-0.2.dist-info/LICENSE
atmodata-0.2.dist-info/METADATA
atmodata-0.2.dist-info/WHEEL
atmodata-0.2.dist-info/top_level.txt
atmodata-0.2.dist-info/RECORD
